<?xml version="1.0" encoding="UTF-8"?>

  <GetCategoryInfoResponse xmlns="urn:ebay:apis:eBLBaseComponents">
   <Timestamp>2018-02-23T09:13:03.035Z</Timestamp>
   <Ack>Success</Ack>
   <Build>E1033_CORE_APILW_18572766_R1</Build>
   <Version>1033</Version>
   <CategoryArray>
    <Category>
     <CategoryID>37958</CategoryID>
     <CategoryLevel>2</CategoryLevel>
     <CategoryName>Maps Atlases and Globes</CategoryName>
     <CategoryParentID>20081</CategoryParentID>
     <CategoryNamePath>Antiques:Maps Atlases and Globes</CategoryNamePath>
     <CategoryIDPath>20081:37958</CategoryIDPath>
     <LeafCategory>false</LeafCategory>
    </Category>
    <Category>
     <CategoryID>98448</CategoryID>
     <CategoryLevel>3</CategoryLevel>
     <CategoryName>Africa Maps</CategoryName>
     <CategoryParentID>37958</CategoryParentID>
     <CategoryNamePath>Antiques:Maps Atlases and Globes:Africa Maps</CategoryNamePath>
     <CategoryIDPath>20081:37958:98448</CategoryIDPath>
     <LeafCategory>true</LeafCategory>
    </Category>
    <Category>
     <CategoryID>98450</CategoryID>
     <CategoryLevel>3</CategoryLevel>
     <CategoryName>Asia Maps</CategoryName>
     <CategoryParentID>37958</CategoryParentID>
     <CategoryNamePath>Antiques:Maps Atlases and Globes:Asia Maps</CategoryNamePath>
     <CategoryIDPath>20081:37958:98450</CategoryIDPath>
     <LeafCategory>true</LeafCategory>
    </Category>
    <Category>
     <CategoryID>98462</CategoryID>
     <CategoryLevel>3</CategoryLevel>
     <CategoryName>Australia/Oceania Maps</CategoryName>
     <CategoryParentID>37958</CategoryParentID>
     <CategoryNamePath>Antiques:Maps Atlases and Globes:Australia/Oceania Maps</CategoryNamePath>
     <CategoryIDPath>20081:37958:98462</CategoryIDPath>
     <LeafCategory>true</LeafCategory>
    </Category>
    <Category>
     <CategoryID>98452</CategoryID>
     <CategoryLevel>3</CategoryLevel>
     <CategoryName>Central America/Caribbean Maps</CategoryName>
     <CategoryParentID>37958</CategoryParentID>
     <CategoryNamePath>Antiques:Maps Atlases and Globes:Central America/Caribbean Maps</CategoryNamePath>
     <CategoryIDPath>20081:37958:98452</CategoryIDPath>
     <LeafCategory>true</LeafCategory>
    </Category>
    <Category>
     <CategoryID>98454</CategoryID>
     <CategoryLevel>3</CategoryLevel>
     <CategoryName>Europe Maps</CategoryName>
     <CategoryParentID>37958</CategoryParentID>
     <CategoryNamePath>Antiques:Maps Atlases and Globes:Europe Maps</CategoryNamePath>
     <CategoryIDPath>20081:37958:98454</CategoryIDPath>
     <LeafCategory>true</LeafCategory>
    </Category>
    <Category>
     <CategoryID>179654</CategoryID>
     <CategoryLevel>3</CategoryLevel>
     <CategoryName>North America Maps</CategoryName>
     <CategoryParentID>37958</CategoryParentID>
     <CategoryNamePath>Antiques:Maps Atlases and Globes:North America Maps</CategoryNamePath>
     <CategoryIDPath>20081:37958:179654</CategoryIDPath>
     <LeafCategory>true</LeafCategory>
    </Category>
    <Category>
     <CategoryID>98464</CategoryID>
     <CategoryLevel>3</CategoryLevel>
     <CategoryName>South America Maps</CategoryName>
     <CategoryParentID>37958</CategoryParentID>
     <CategoryNamePath>Antiques:Maps Atlases and Globes:South America Maps</CategoryNamePath>
     <CategoryIDPath>20081:37958:98464</CategoryIDPath>
     <LeafCategory>true</LeafCategory>
    </Category>
    <Category>
     <CategoryID>98466</CategoryID>
     <CategoryLevel>3</CategoryLevel>
     <CategoryName>World Maps</CategoryName>
     <CategoryParentID>37958</CategoryParentID>
     <CategoryNamePath>Antiques:Maps Atlases and Globes:World Maps</CategoryNamePath>
     <CategoryIDPath>20081:37958:98466</CategoryIDPath>
     <LeafCategory>true</LeafCategory>
    </Category>
    <Category>
     <CategoryID>184438</CategoryID>
     <CategoryLevel>3</CategoryLevel>
     <CategoryName>Celestial Maps</CategoryName>
     <CategoryParentID>37958</CategoryParentID>
     <CategoryNamePath>Antiques:Maps Atlases and Globes:Celestial Maps</CategoryNamePath>
     <CategoryIDPath>20081:37958:184438</CategoryIDPath>
     <LeafCategory>true</LeafCategory>
    </Category>
    <Category>
     <CategoryID>184439</CategoryID>
     <CategoryLevel>3</CategoryLevel>
     <CategoryName>Curiosities Maps</CategoryName>
     <CategoryParentID>37958</CategoryParentID>
     <CategoryNamePath>Antiques:Maps Atlases and Globes:Curiosities Maps</CategoryNamePath>
     <CategoryIDPath>20081:37958:184439</CategoryIDPath>
     <LeafCategory>true</LeafCategory>
    </Category>
    <Category>
     <CategoryID>63595</CategoryID>
     <CategoryLevel>3</CategoryLevel>
     <CategoryName>Digital Maps</CategoryName>
     <CategoryParentID>37958</CategoryParentID>
     <CategoryNamePath>Antiques:Maps Atlases and Globes:Digital Maps</CategoryNamePath>
     <CategoryIDPath>20081:37958:63595</CategoryIDPath>
     <LeafCategory>true</LeafCategory>
    </Category>
    <Category>
     <CategoryID>98468</CategoryID>
     <CategoryLevel>3</CategoryLevel>
     <CategoryName>World and Celestial Globes</CategoryName>
     <CategoryParentID>37958</CategoryParentID>
     <CategoryNamePath>Antiques:Maps Atlases and Globes:World and Celestial Globes</CategoryNamePath>
     <CategoryIDPath>20081:37958:98468</CategoryIDPath>
     <LeafCategory>true</LeafCategory>
    </Category>
    <Category>
     <CategoryID>37964</CategoryID>
     <CategoryLevel>3</CategoryLevel>
     <CategoryName>Map and Globe Mixed Lots</CategoryName>
     <CategoryParentID>37958</CategoryParentID>
     <CategoryNamePath>Antiques:Maps Atlases and Globes:Map and Globe Mixed Lots</CategoryNamePath>
     <CategoryIDPath>20081:37958:37964</CategoryIDPath>
     <LeafCategory>true</LeafCategory>
    </Category>
    <Category>
     <CategoryID>151725</CategoryID>
     <CategoryLevel>3</CategoryLevel>
     <CategoryName>Map and Globe Reproductions</CategoryName>
     <CategoryParentID>37958</CategoryParentID>
     <CategoryNamePath>Antiques:Maps Atlases and Globes:Map and Globe Reproductions</CategoryNamePath>
     <CategoryIDPath>20081:37958:151725</CategoryIDPath>
     <LeafCategory>true</LeafCategory>
    </Category>
   </CategoryArray>
   <CategoryCount>15</CategoryCount>
   <UpdateTime>2017-06-02T23:04:46.000Z</UpdateTime>
   <CategoryVersion>117</CategoryVersion>
  </GetCategoryInfoResponse>
 