<?xml version="1.0" encoding="UTF-8"?>

  <GetCategoryInfoResponse xmlns="urn:ebay:apis:eBLBaseComponents">
   <Timestamp>2018-02-23T09:13:11.535Z</Timestamp>
   <Ack>Success</Ack>
   <Build>E1033_CORE_APILW_18572766_R1</Build>
   <Version>1033</Version>
   <CategoryArray>
    <Category>
     <CategoryID>181726</CategoryID>
     <CategoryLevel>2</CategoryLevel>
     <CategoryName>Musical Instruments (Pre-1930)</CategoryName>
     <CategoryParentID>20081</CategoryParentID>
     <CategoryNamePath>Antiques:Musical Instruments (Pre-1930)</CategoryNamePath>
     <CategoryIDPath>20081:181726</CategoryIDPath>
     <LeafCategory>false</LeafCategory>
    </Category>
    <Category>
     <CategoryID>156320</CategoryID>
     <CategoryLevel>3</CategoryLevel>
     <CategoryName>Brass</CategoryName>
     <CategoryParentID>181726</CategoryParentID>
     <CategoryNamePath>Antiques:Musical Instruments (Pre-1930):Brass</CategoryNamePath>
     <CategoryIDPath>20081:181726:156320</CategoryIDPath>
     <LeafCategory>true</LeafCategory>
    </Category>
    <Category>
     <CategoryID>37975</CategoryID>
     <CategoryLevel>3</CategoryLevel>
     <CategoryName>Keyboard</CategoryName>
     <CategoryParentID>181726</CategoryParentID>
     <CategoryNamePath>Antiques:Musical Instruments (Pre-1930):Keyboard</CategoryNamePath>
     <CategoryIDPath>20081:181726:37975</CategoryIDPath>
     <LeafCategory>true</LeafCategory>
    </Category>
    <Category>
     <CategoryID>37976</CategoryID>
     <CategoryLevel>3</CategoryLevel>
     <CategoryName>Percussion</CategoryName>
     <CategoryParentID>181726</CategoryParentID>
     <CategoryNamePath>Antiques:Musical Instruments (Pre-1930):Percussion</CategoryNamePath>
     <CategoryIDPath>20081:181726:37976</CategoryIDPath>
     <LeafCategory>true</LeafCategory>
    </Category>
    <Category>
     <CategoryID>181727</CategoryID>
     <CategoryLevel>3</CategoryLevel>
     <CategoryName>String</CategoryName>
     <CategoryParentID>181726</CategoryParentID>
     <CategoryNamePath>Antiques:Musical Instruments (Pre-1930):String</CategoryNamePath>
     <CategoryIDPath>20081:181726:181727</CategoryIDPath>
     <LeafCategory>true</LeafCategory>
    </Category>
    <Category>
     <CategoryID>37977</CategoryID>
     <CategoryLevel>3</CategoryLevel>
     <CategoryName>Wind</CategoryName>
     <CategoryParentID>181726</CategoryParentID>
     <CategoryNamePath>Antiques:Musical Instruments (Pre-1930):Wind</CategoryNamePath>
     <CategoryIDPath>20081:181726:37977</CategoryIDPath>
     <LeafCategory>true</LeafCategory>
    </Category>
    <Category>
     <CategoryID>156321</CategoryID>
     <CategoryLevel>3</CategoryLevel>
     <CategoryName>Reproductions</CategoryName>
     <CategoryParentID>181726</CategoryParentID>
     <CategoryNamePath>Antiques:Musical Instruments (Pre-1930):Reproductions</CategoryNamePath>
     <CategoryIDPath>20081:181726:156321</CategoryIDPath>
     <LeafCategory>true</LeafCategory>
    </Category>
    <Category>
     <CategoryID>171176</CategoryID>
     <CategoryLevel>3</CategoryLevel>
     <CategoryName>Price Guides and Publications</CategoryName>
     <CategoryParentID>181726</CategoryParentID>
     <CategoryNamePath>Antiques:Musical Instruments (Pre-1930):Price Guides and Publications</CategoryNamePath>
     <CategoryIDPath>20081:181726:171176</CategoryIDPath>
     <LeafCategory>true</LeafCategory>
    </Category>
    <Category>
     <CategoryID>156322</CategoryID>
     <CategoryLevel>3</CategoryLevel>
     <CategoryName>Other Antique Instruments</CategoryName>
     <CategoryParentID>181726</CategoryParentID>
     <CategoryNamePath>Antiques:Musical Instruments (Pre-1930):Other Antique Instruments</CategoryNamePath>
     <CategoryIDPath>20081:181726:156322</CategoryIDPath>
     <LeafCategory>true</LeafCategory>
    </Category>
   </CategoryArray>
   <CategoryCount>9</CategoryCount>
   <UpdateTime>2017-06-02T23:04:46.000Z</UpdateTime>
   <CategoryVersion>117</CategoryVersion>
  </GetCategoryInfoResponse>
 