<?xml version="1.0" encoding="UTF-8"?>

  <GetCategoryInfoResponse xmlns="urn:ebay:apis:eBLBaseComponents">
   <Timestamp>2018-02-23T09:14:16.082Z</Timestamp>
   <Ack>Success</Ack>
   <Build>E1033_CORE_APILW_18572766_R1</Build>
   <Version>1033</Version>
   <CategoryArray>
    <Category>
     <CategoryID>11765</CategoryID>
     <CategoryLevel>2</CategoryLevel>
     <CategoryName>Construction</CategoryName>
     <CategoryParentID>12576</CategoryParentID>
     <CategoryNamePath>Business and Industrial:Construction</CategoryNamePath>
     <CategoryIDPath>12576:11765</CategoryIDPath>
     <LeafCategory>false</LeafCategory>
    </Category>
    <Category>
     <CategoryID>41498</CategoryID>
     <CategoryLevel>3</CategoryLevel>
     <CategoryName>Building Materials and Supplies</CategoryName>
     <CategoryParentID>11765</CategoryParentID>
     <CategoryNamePath>Business and Industrial:Construction:Building Materials and Supplies</CategoryNamePath>
     <CategoryIDPath>12576:11765:41498</CategoryIDPath>
     <LeafCategory>false</LeafCategory>
    </Category>
    <Category>
     <CategoryID>55805</CategoryID>
     <CategoryLevel>3</CategoryLevel>
     <CategoryName>Buildings Modular and Pre-Fab</CategoryName>
     <CategoryParentID>11765</CategoryParentID>
     <CategoryNamePath>Business and Industrial:Construction:Buildings Modular and Pre-Fab</CategoryNamePath>
     <CategoryIDPath>12576:11765:55805</CategoryIDPath>
     <LeafCategory>true</LeafCategory>
    </Category>
    <Category>
     <CategoryID>42297</CategoryID>
     <CategoryLevel>3</CategoryLevel>
     <CategoryName>Levels and Surveying Equipment</CategoryName>
     <CategoryParentID>11765</CategoryParentID>
     <CategoryNamePath>Business and Industrial:Construction:Levels and Surveying Equipment</CategoryNamePath>
     <CategoryIDPath>12576:11765:42297</CategoryIDPath>
     <LeafCategory>false</LeafCategory>
    </Category>
    <Category>
     <CategoryID>92152</CategoryID>
     <CategoryLevel>3</CategoryLevel>
     <CategoryName>Mining Equipment</CategoryName>
     <CategoryParentID>11765</CategoryParentID>
     <CategoryNamePath>Business and Industrial:Construction:Mining Equipment</CategoryNamePath>
     <CategoryIDPath>12576:11765:92152</CategoryIDPath>
     <LeafCategory>true</LeafCategory>
    </Category>
    <Category>
     <CategoryID>63908</CategoryID>
     <CategoryLevel>3</CategoryLevel>
     <CategoryName>Protective Gear</CategoryName>
     <CategoryParentID>11765</CategoryParentID>
     <CategoryNamePath>Business and Industrial:Construction:Protective Gear</CategoryNamePath>
     <CategoryIDPath>12576:11765:63908</CategoryIDPath>
     <LeafCategory>false</LeafCategory>
    </Category>
    <Category>
     <CategoryID>116996</CategoryID>
     <CategoryLevel>3</CategoryLevel>
     <CategoryName>Vintage Construction</CategoryName>
     <CategoryParentID>11765</CategoryParentID>
     <CategoryNamePath>Business and Industrial:Construction:Vintage Construction</CategoryNamePath>
     <CategoryIDPath>12576:11765:116996</CategoryIDPath>
     <LeafCategory>false</LeafCategory>
    </Category>
    <Category>
     <CategoryID>1268</CategoryID>
     <CategoryLevel>3</CategoryLevel>
     <CategoryName>Other Construction</CategoryName>
     <CategoryParentID>11765</CategoryParentID>
     <CategoryNamePath>Business and Industrial:Construction:Other Construction</CategoryNamePath>
     <CategoryIDPath>12576:11765:1268</CategoryIDPath>
     <LeafCategory>true</LeafCategory>
    </Category>
    <Category>
     <CategoryID>56139</CategoryID>
     <CategoryLevel>3</CategoryLevel>
     <CategoryName>Wholesale Lots</CategoryName>
     <CategoryParentID>11765</CategoryParentID>
     <CategoryNamePath>Business and Industrial:Construction:Wholesale Lots</CategoryNamePath>
     <CategoryIDPath>12576:11765:56139</CategoryIDPath>
     <LeafCategory>true</LeafCategory>
    </Category>
   </CategoryArray>
   <CategoryCount>9</CategoryCount>
   <UpdateTime>2017-06-02T23:04:46.000Z</UpdateTime>
   <CategoryVersion>117</CategoryVersion>
  </GetCategoryInfoResponse>
 