<?xml version="1.0" encoding="UTF-8"?>

  <GetCategoryInfoResponse xmlns="urn:ebay:apis:eBLBaseComponents">
   <Timestamp>2018-02-23T11:03:07.299Z</Timestamp>
   <Ack>Success</Ack>
   <Build>E1033_CORE_APILW_18572766_R1</Build>
   <Version>1033</Version>
   <CategoryArray>
    <Category>
     <CategoryID>63757</CategoryID>
     <CategoryLevel>4</CategoryLevel>
     <CategoryName>Sets</CategoryName>
     <CategoryParentID>35743</CategoryParentID>
     <CategoryNamePath>Collectibles:Casino:Chips:Sets</CategoryNamePath>
     <CategoryIDPath>1:898:35743:63757</CategoryIDPath>
     <LeafCategory>false</LeafCategory>
    </Category>
    <Category>
     <CategoryID>63758</CategoryID>
     <CategoryLevel>5</CategoryLevel>
     <CategoryName>300</CategoryName>
     <CategoryParentID>63757</CategoryParentID>
     <CategoryNamePath>Collectibles:Casino:Chips:Sets:300</CategoryNamePath>
     <CategoryIDPath>1:898:35743:63757:63758</CategoryIDPath>
     <LeafCategory>true</LeafCategory>
    </Category>
    <Category>
     <CategoryID>70957</CategoryID>
     <CategoryLevel>5</CategoryLevel>
     <CategoryName>400</CategoryName>
     <CategoryParentID>63757</CategoryParentID>
     <CategoryNamePath>Collectibles:Casino:Chips:Sets:400</CategoryNamePath>
     <CategoryIDPath>1:898:35743:63757:70957</CategoryIDPath>
     <LeafCategory>true</LeafCategory>
    </Category>
    <Category>
     <CategoryID>63759</CategoryID>
     <CategoryLevel>5</CategoryLevel>
     <CategoryName>500</CategoryName>
     <CategoryParentID>63757</CategoryParentID>
     <CategoryNamePath>Collectibles:Casino:Chips:Sets:500</CategoryNamePath>
     <CategoryIDPath>1:898:35743:63757:63759</CategoryIDPath>
     <LeafCategory>true</LeafCategory>
    </Category>
    <Category>
     <CategoryID>70958</CategoryID>
     <CategoryLevel>5</CategoryLevel>
     <CategoryName>600</CategoryName>
     <CategoryParentID>63757</CategoryParentID>
     <CategoryNamePath>Collectibles:Casino:Chips:Sets:600</CategoryNamePath>
     <CategoryIDPath>1:898:35743:63757:70958</CategoryIDPath>
     <LeafCategory>true</LeafCategory>
    </Category>
    <Category>
     <CategoryID>70959</CategoryID>
     <CategoryLevel>5</CategoryLevel>
     <CategoryName>650</CategoryName>
     <CategoryParentID>63757</CategoryParentID>
     <CategoryNamePath>Collectibles:Casino:Chips:Sets:650</CategoryNamePath>
     <CategoryIDPath>1:898:35743:63757:70959</CategoryIDPath>
     <LeafCategory>true</LeafCategory>
    </Category>
    <Category>
     <CategoryID>95115</CategoryID>
     <CategoryLevel>5</CategoryLevel>
     <CategoryName>1000</CategoryName>
     <CategoryParentID>63757</CategoryParentID>
     <CategoryNamePath>Collectibles:Casino:Chips:Sets:1000</CategoryNamePath>
     <CategoryIDPath>1:898:35743:63757:95115</CategoryIDPath>
     <LeafCategory>true</LeafCategory>
    </Category>
    <Category>
     <CategoryID>63760</CategoryID>
     <CategoryLevel>5</CategoryLevel>
     <CategoryName>Other Casino Chip Sets</CategoryName>
     <CategoryParentID>63757</CategoryParentID>
     <CategoryNamePath>Collectibles:Casino:Chips:Sets:Other Casino Chip Sets</CategoryNamePath>
     <CategoryIDPath>1:898:35743:63757:63760</CategoryIDPath>
     <LeafCategory>true</LeafCategory>
    </Category>
   </CategoryArray>
   <CategoryCount>8</CategoryCount>
   <UpdateTime>2017-06-02T23:04:46.000Z</UpdateTime>
   <CategoryVersion>117</CategoryVersion>
  </GetCategoryInfoResponse>
 