<?xml version="1.0" encoding="UTF-8"?>

  <GetCategoryInfoResponse xmlns="urn:ebay:apis:eBLBaseComponents">
   <Timestamp>2018-02-23T11:27:40.457Z</Timestamp>
   <Ack>Success</Ack>
   <Build>E1033_CORE_APILW_18572766_R1</Build>
   <Version>1033</Version>
   <CategoryArray>
    <Category>
     <CategoryID>163956</CategoryID>
     <CategoryLevel>4</CategoryLevel>
     <CategoryName>Concert Memorabilia</CategoryName>
     <CategoryParentID>2337</CategoryParentID>
     <CategoryNamePath>Entertainment Memorabilia:Music Memorabilia:Country:Concert Memorabilia</CategoryNamePath>
     <CategoryIDPath>45100:2329:2337:163956</CategoryIDPath>
     <LeafCategory>false</LeafCategory>
    </Category>
    <Category>
     <CategoryID>163957</CategoryID>
     <CategoryLevel>5</CategoryLevel>
     <CategoryName>Backstage Passes</CategoryName>
     <CategoryParentID>163956</CategoryParentID>
     <CategoryNamePath>Entertainment Memorabilia:Music Memorabilia:Country:Concert Memorabilia:Backstage Passes</CategoryNamePath>
     <CategoryIDPath>45100:2329:2337:163956:163957</CategoryIDPath>
     <LeafCategory>true</LeafCategory>
    </Category>
    <Category>
     <CategoryID>163958</CategoryID>
     <CategoryLevel>5</CategoryLevel>
     <CategoryName>Guitar Picks</CategoryName>
     <CategoryParentID>163956</CategoryParentID>
     <CategoryNamePath>Entertainment Memorabilia:Music Memorabilia:Country:Concert Memorabilia:Guitar Picks</CategoryNamePath>
     <CategoryIDPath>45100:2329:2337:163956:163958</CategoryIDPath>
     <LeafCategory>true</LeafCategory>
    </Category>
    <Category>
     <CategoryID>163959</CategoryID>
     <CategoryLevel>5</CategoryLevel>
     <CategoryName>Programs</CategoryName>
     <CategoryParentID>163956</CategoryParentID>
     <CategoryNamePath>Entertainment Memorabilia:Music Memorabilia:Country:Concert Memorabilia:Programs</CategoryNamePath>
     <CategoryIDPath>45100:2329:2337:163956:163959</CategoryIDPath>
     <LeafCategory>true</LeafCategory>
    </Category>
    <Category>
     <CategoryID>163960</CategoryID>
     <CategoryLevel>5</CategoryLevel>
     <CategoryName>Tickets and Stubs</CategoryName>
     <CategoryParentID>163956</CategoryParentID>
     <CategoryNamePath>Entertainment Memorabilia:Music Memorabilia:Country:Concert Memorabilia:Tickets and Stubs</CategoryNamePath>
     <CategoryIDPath>45100:2329:2337:163956:163960</CategoryIDPath>
     <LeafCategory>true</LeafCategory>
    </Category>
    <Category>
     <CategoryID>108738</CategoryID>
     <CategoryLevel>5</CategoryLevel>
     <CategoryName>Other Country Concert Mem</CategoryName>
     <CategoryParentID>163956</CategoryParentID>
     <CategoryNamePath>Entertainment Memorabilia:Music Memorabilia:Country:Concert Memorabilia:Other Country Concert Mem</CategoryNamePath>
     <CategoryIDPath>45100:2329:2337:163956:108738</CategoryIDPath>
     <LeafCategory>true</LeafCategory>
    </Category>
   </CategoryArray>
   <CategoryCount>6</CategoryCount>
   <UpdateTime>2017-06-02T23:04:46.000Z</UpdateTime>
   <CategoryVersion>117</CategoryVersion>
  </GetCategoryInfoResponse>
 