<?xml version="1.0" encoding="UTF-8"?>

  <GetCategoryInfoResponse xmlns="urn:ebay:apis:eBLBaseComponents">
   <Timestamp>2018-02-23T11:12:35.517Z</Timestamp>
   <Ack>Success</Ack>
   <Build>E1033_CORE_APILW_18572766_R1</Build>
   <Version>1033</Version>
   <CategoryArray>
    <Category>
     <CategoryID>156490</CategoryID>
     <CategoryLevel>4</CategoryLevel>
     <CategoryName>1900-49</CategoryName>
     <CategoryParentID>156488</CategoryParentID>
     <CategoryNamePath>Collectibles:Paper:Correspondence:1900-49</CategoryNamePath>
     <CategoryIDPath>1:124:156488:156490</CategoryIDPath>
     <LeafCategory>true</LeafCategory>
    </Category>
   </CategoryArray>
   <CategoryCount>1</CategoryCount>
   <UpdateTime>2018-02-17T00:14:11.000Z</UpdateTime>
   <CategoryVersion>118</CategoryVersion>
  </GetCategoryInfoResponse>
 