<?xml version="1.0" encoding="UTF-8"?>

  <GetCategoryInfoResponse xmlns="urn:ebay:apis:eBLBaseComponents">
   <Timestamp>2018-02-23T10:48:45.017Z</Timestamp>
   <Ack>Success</Ack>
   <Build>E1033_CORE_APILW_18572766_R1</Build>
   <Version>1033</Version>
   <CategoryArray>
    <Category>
     <CategoryID>167900</CategoryID>
     <CategoryLevel>4</CategoryLevel>
     <CategoryName>Vintage Signs and Décor</CategoryName>
     <CategoryParentID>57093</CategoryParentID>
     <CategoryNamePath>Business and Industrial:Restaurant and Catering:Furniture Signs and Décor:Vintage Signs and Décor</CategoryNamePath>
     <CategoryIDPath>12576:11874:57093:167900</CategoryIDPath>
     <LeafCategory>true</LeafCategory>
    </Category>
   </CategoryArray>
   <CategoryCount>1</CategoryCount>
   <UpdateTime>2018-02-17T00:14:11.000Z</UpdateTime>
   <CategoryVersion>118</CategoryVersion>
  </GetCategoryInfoResponse>
 