<?xml version="1.0" encoding="UTF-8"?>

  <GetCategoryInfoResponse xmlns="urn:ebay:apis:eBLBaseComponents">
   <Timestamp>2018-02-23T11:35:25.767Z</Timestamp>
   <Ack>Success</Ack>
   <Build>E1033_CORE_APILW_18572766_R1</Build>
   <Version>1033</Version>
   <CategoryArray>
    <Category>
     <CategoryID>42249</CategoryID>
     <CategoryLevel>4</CategoryLevel>
     <CategoryName>Sanders</CategoryName>
     <CategoryParentID>22659</CategoryParentID>
     <CategoryNamePath>Home and Garden:Tools:Air Tools:Sanders</CategoryNamePath>
     <CategoryIDPath>11700:631:22659:42249</CategoryIDPath>
     <LeafCategory>true</LeafCategory>
    </Category>
   </CategoryArray>
   <CategoryCount>1</CategoryCount>
   <UpdateTime>2018-02-17T00:14:11.000Z</UpdateTime>
   <CategoryVersion>118</CategoryVersion>
  </GetCategoryInfoResponse>
 