<?xml version="1.0" encoding="UTF-8"?>

  <GetCategoryInfoResponse xmlns="urn:ebay:apis:eBLBaseComponents">
   <Timestamp>2018-02-23T11:18:56.879Z</Timestamp>
   <Ack>Success</Ack>
   <Build>E1033_CORE_APILW_18572766_R1</Build>
   <Version>1033</Version>
   <CategoryArray>
    <Category>
     <CategoryID>74953</CategoryID>
     <CategoryLevel>4</CategoryLevel>
     <CategoryName>Laptop Modem Cards</CategoryName>
     <CategoryParentID>42190</CategoryParentID>
     <CategoryNamePath>Computers/Tablets and Networking:Laptop and Desktop Accessories:Laptop Add-On Cards:Laptop Modem Cards</CategoryNamePath>
     <CategoryIDPath>58058:31530:42190:74953</CategoryIDPath>
     <LeafCategory>true</LeafCategory>
    </Category>
   </CategoryArray>
   <CategoryCount>1</CategoryCount>
   <UpdateTime>2017-06-02T23:04:46.000Z</UpdateTime>
   <CategoryVersion>117</CategoryVersion>
  </GetCategoryInfoResponse>
 