<?xml version="1.0" encoding="UTF-8"?>

  <GetCategoryInfoResponse xmlns="urn:ebay:apis:eBLBaseComponents">
   <Timestamp>2018-02-23T10:17:12.142Z</Timestamp>
   <Ack>Success</Ack>
   <Build>E1033_CORE_APILW_18572766_R1</Build>
   <Version>1033</Version>
   <CategoryArray>
    <Category>
     <CategoryID>181225</CategoryID>
     <CategoryLevel>3</CategoryLevel>
     <CategoryName>Pianos</CategoryName>
     <CategoryParentID>180010</CategoryParentID>
     <CategoryNamePath>Musical Instruments and Gear:Pianos Keyboards and Organs:Pianos</CategoryNamePath>
     <CategoryIDPath>619:180010:181225</CategoryIDPath>
     <LeafCategory>false</LeafCategory>
    </Category>
    <Category>
     <CategoryID>43376</CategoryID>
     <CategoryLevel>4</CategoryLevel>
     <CategoryName>Grand and Baby Grand Pianos</CategoryName>
     <CategoryParentID>181225</CategoryParentID>
     <CategoryNamePath>Musical Instruments and Gear:Pianos Keyboards and Organs:Pianos:Grand and Baby Grand Pianos</CategoryNamePath>
     <CategoryIDPath>619:180010:181225:43376</CategoryIDPath>
     <LeafCategory>true</LeafCategory>
    </Category>
    <Category>
     <CategoryID>85860</CategoryID>
     <CategoryLevel>4</CategoryLevel>
     <CategoryName>Digital Pianos</CategoryName>
     <CategoryParentID>181225</CategoryParentID>
     <CategoryNamePath>Musical Instruments and Gear:Pianos Keyboards and Organs:Pianos:Digital Pianos</CategoryNamePath>
     <CategoryIDPath>619:180010:181225:85860</CategoryIDPath>
     <LeafCategory>true</LeafCategory>
    </Category>
    <Category>
     <CategoryID>43377</CategoryID>
     <CategoryLevel>4</CategoryLevel>
     <CategoryName>Upright Pianos</CategoryName>
     <CategoryParentID>181225</CategoryParentID>
     <CategoryNamePath>Musical Instruments and Gear:Pianos Keyboards and Organs:Pianos:Upright Pianos</CategoryNamePath>
     <CategoryIDPath>619:180010:181225:43377</CategoryIDPath>
     <LeafCategory>true</LeafCategory>
    </Category>
    <Category>
     <CategoryID>16220</CategoryID>
     <CategoryLevel>4</CategoryLevel>
     <CategoryName>Other Pianos</CategoryName>
     <CategoryParentID>181225</CategoryParentID>
     <CategoryNamePath>Musical Instruments and Gear:Pianos Keyboards and Organs:Pianos:Other Pianos</CategoryNamePath>
     <CategoryIDPath>619:180010:181225:16220</CategoryIDPath>
     <LeafCategory>true</LeafCategory>
    </Category>
   </CategoryArray>
   <CategoryCount>5</CategoryCount>
   <UpdateTime>2018-02-17T00:14:11.000Z</UpdateTime>
   <CategoryVersion>118</CategoryVersion>
  </GetCategoryInfoResponse>
 