<?xml version="1.0" encoding="UTF-8"?>

  <GetCategoryInfoResponse xmlns="urn:ebay:apis:eBLBaseComponents">
   <Timestamp>2018-02-23T09:36:34.565Z</Timestamp>
   <Ack>Success</Ack>
   <Build>E1033_CORE_APILW_18572766_R1</Build>
   <Version>1033</Version>
   <CategoryArray>
    <Category>
     <CategoryID>183925</CategoryID>
     <CategoryLevel>3</CategoryLevel>
     <CategoryName>Rivets</CategoryName>
     <CategoryParentID>183900</CategoryParentID>
     <CategoryNamePath>Business and Industrial:Fasteners and Hardware:Rivets</CategoryNamePath>
     <CategoryIDPath>12576:183900:183925</CategoryIDPath>
     <LeafCategory>false</LeafCategory>
    </Category>
    <Category>
     <CategoryID>183926</CategoryID>
     <CategoryLevel>4</CategoryLevel>
     <CategoryName>Blind and Drive Rivets</CategoryName>
     <CategoryParentID>183925</CategoryParentID>
     <CategoryNamePath>Business and Industrial:Fasteners and Hardware:Rivets:Blind and Drive Rivets</CategoryNamePath>
     <CategoryIDPath>12576:183900:183925:183926</CategoryIDPath>
     <LeafCategory>true</LeafCategory>
    </Category>
    <Category>
     <CategoryID>183927</CategoryID>
     <CategoryLevel>4</CategoryLevel>
     <CategoryName>Push-In Rivets</CategoryName>
     <CategoryParentID>183925</CategoryParentID>
     <CategoryNamePath>Business and Industrial:Fasteners and Hardware:Rivets:Push-In Rivets</CategoryNamePath>
     <CategoryIDPath>12576:183900:183925:183927</CategoryIDPath>
     <LeafCategory>true</LeafCategory>
    </Category>
    <Category>
     <CategoryID>183928</CategoryID>
     <CategoryLevel>4</CategoryLevel>
     <CategoryName>Solid Rivets</CategoryName>
     <CategoryParentID>183925</CategoryParentID>
     <CategoryNamePath>Business and Industrial:Fasteners and Hardware:Rivets:Solid Rivets</CategoryNamePath>
     <CategoryIDPath>12576:183900:183925:183928</CategoryIDPath>
     <LeafCategory>true</LeafCategory>
    </Category>
    <Category>
     <CategoryID>183929</CategoryID>
     <CategoryLevel>4</CategoryLevel>
     <CategoryName>Split Rivets</CategoryName>
     <CategoryParentID>183925</CategoryParentID>
     <CategoryNamePath>Business and Industrial:Fasteners and Hardware:Rivets:Split Rivets</CategoryNamePath>
     <CategoryIDPath>12576:183900:183925:183929</CategoryIDPath>
     <LeafCategory>true</LeafCategory>
    </Category>
    <Category>
     <CategoryID>183930</CategoryID>
     <CategoryLevel>4</CategoryLevel>
     <CategoryName>Tubular and Semi-Tubular Rivets</CategoryName>
     <CategoryParentID>183925</CategoryParentID>
     <CategoryNamePath>Business and Industrial:Fasteners and Hardware:Rivets:Tubular and Semi-Tubular Rivets</CategoryNamePath>
     <CategoryIDPath>12576:183900:183925:183930</CategoryIDPath>
     <LeafCategory>true</LeafCategory>
    </Category>
   </CategoryArray>
   <CategoryCount>6</CategoryCount>
   <UpdateTime>2017-06-02T23:04:46.000Z</UpdateTime>
   <CategoryVersion>117</CategoryVersion>
  </GetCategoryInfoResponse>
 