<?xml version="1.0" encoding="UTF-8"?>

  <GetCategoryInfoResponse xmlns="urn:ebay:apis:eBLBaseComponents">
   <Timestamp>2018-02-23T09:33:50.580Z</Timestamp>
   <Ack>Success</Ack>
   <Build>E1033_CORE_APILW_18572766_R1</Build>
   <Version>1033</Version>
   <CategoryArray>
    <Category>
     <CategoryID>162024</CategoryID>
     <CategoryLevel>3</CategoryLevel>
     <CategoryName>Bath Tub Seats and Rings</CategoryName>
     <CategoryParentID>20394</CategoryParentID>
     <CategoryNamePath>Baby:Bathing and Grooming:Bath Tub Seats and Rings</CategoryNamePath>
     <CategoryIDPath>2984:20394:162024</CategoryIDPath>
     <LeafCategory>true</LeafCategory>
    </Category>
   </CategoryArray>
   <CategoryCount>1</CategoryCount>
   <UpdateTime>2017-06-02T23:04:46.000Z</UpdateTime>
   <CategoryVersion>117</CategoryVersion>
  </GetCategoryInfoResponse>
 