<?xml version="1.0" encoding="UTF-8"?>

  <GetCategoryInfoResponse xmlns="urn:ebay:apis:eBLBaseComponents">
   <Timestamp>2018-02-23T10:29:37.502Z</Timestamp>
   <Ack>Success</Ack>
   <Build>E1033_CORE_APILW_18572766_R1</Build>
   <Version>1033</Version>
   <CategoryArray>
    <Category>
     <CategoryID>28811</CategoryID>
     <CategoryLevel>3</CategoryLevel>
     <CategoryName>Meccano and Erector Sets</CategoryName>
     <CategoryParentID>183446</CategoryParentID>
     <CategoryNamePath>Toys and Hobbies:Building Toys:Meccano and Erector Sets</CategoryNamePath>
     <CategoryIDPath>220:183446:28811</CategoryIDPath>
     <LeafCategory>false</LeafCategory>
    </Category>
    <Category>
     <CategoryID>724</CategoryID>
     <CategoryLevel>4</CategoryLevel>
     <CategoryName>Pre-1980</CategoryName>
     <CategoryParentID>28811</CategoryParentID>
     <CategoryNamePath>Toys and Hobbies:Building Toys:Meccano and Erector Sets:Pre-1980</CategoryNamePath>
     <CategoryIDPath>220:183446:28811:724</CategoryIDPath>
     <LeafCategory>true</LeafCategory>
    </Category>
    <Category>
     <CategoryID>4318</CategoryID>
     <CategoryLevel>4</CategoryLevel>
     <CategoryName>1980-Now</CategoryName>
     <CategoryParentID>28811</CategoryParentID>
     <CategoryNamePath>Toys and Hobbies:Building Toys:Meccano and Erector Sets:1980-Now</CategoryNamePath>
     <CategoryIDPath>220:183446:28811:4318</CategoryIDPath>
     <LeafCategory>true</LeafCategory>
    </Category>
   </CategoryArray>
   <CategoryCount>3</CategoryCount>
   <UpdateTime>2017-06-02T23:04:46.000Z</UpdateTime>
   <CategoryVersion>117</CategoryVersion>
  </GetCategoryInfoResponse>
 